MeowCore/__init__.py
MeowCore/main.py
MeowCore/welcome.py
MeowCore/welcome_func.py
MeowCore-0.0.7.dist-info/LICENSE
MeowCore-0.0.7.dist-info/METADATA
MeowCore-0.0.7.dist-info/WHEEL
MeowCore-0.0.7.dist-info/top_level.txt
MeowCore-0.0.7.dist-info/RECORD
